bbcgfx/__init__.py
bbcgfx/bbcgfx.py
bbcgfx/screen.py
bbcgfx-0.1.0.dist-info/LICENSE
bbcgfx-0.1.0.dist-info/METADATA
bbcgfx-0.1.0.dist-info/WHEEL
bbcgfx-0.1.0.dist-info/top_level.txt
bbcgfx-0.1.0.dist-info/RECORD
